src/__init__.py
src/main.py
src/managers/__init__.py
src/managers/lambda_function.py
src/models/__init__.py
src/models/layer_config.py
src/utils.py
lambda_layer_manager-0.1.0.dist-info/entry_points.txt
lambda_layer_manager-0.1.0.dist-info/LICENSE
lambda_layer_manager-0.1.0.dist-info/WHEEL
lambda_layer_manager-0.1.0.dist-info/METADATA
lambda_layer_manager-0.1.0.dist-info/RECORD
