Metadata-Version: 2.1
Name: lambda-layer-manager
Version: 0.1.0
Summary: Automatic Lambda Layer Manager
Home-page: https://github.com/MMartin09/lambda_layer
License: MIT
Author: MMartin09
Author-email: mmartin09@outlook.at
Requires-Python: >=3.11,<4.0
Classifier: License :: OSI Approved :: MIT License
Classifier: Programming Language :: Python :: 3
Classifier: Programming Language :: Python :: 3.11
Requires-Dist: boto3 (>=1.26.98,<2.0.0)
Requires-Dist: pydantic (>=1.10.7,<2.0.0)
Requires-Dist: typer (>=0.9.0,<0.10.0)
Project-URL: Repository, https://github.com/MMartin09/lambda_layer
